AgentsWorker/Manager.py
AgentsWorker/RequestAgent.py
AgentsWorker/__init__.py
AgentsWorker/agent.py
AgentsWorker/kafkaBase.py
AgentsWorker/loggs.py
AgentsWorker/options.py
AgentsWorker-1.0.6.dist-info/LICENSE.txt
AgentsWorker-1.0.6.dist-info/METADATA
AgentsWorker-1.0.6.dist-info/WHEEL
AgentsWorker-1.0.6.dist-info/top_level.txt
AgentsWorker-1.0.6.dist-info/RECORD
