Metadata-Version: 2.1
Name: AgentsWorker
Version: 1.0.6
Summary: Libreria para crear agentes que responden a eventos desde kafka
Home-page: UNKNOWN
Author: Enoi Barrera Guzman
Author-email: zafiro3000x@gmail.com
License: UNKNOWN
Platform: UNKNOWN
Classifier: Programming Language :: Python :: 3
Requires-Dist: kafka-python (==1.4.6)
Requires-Dist: Logbook (==1.4.3)
